calibr8/__init__.py
calibr8/core.py
calibr8/optimization.py
calibr8/py.typed
calibr8/test_all.py
calibr8/utils.py
calibr8/__pycache__/__init__.cpython-311.pyc
calibr8/__pycache__/core.cpython-311.pyc
calibr8/__pycache__/optimization.cpython-311.pyc
calibr8/__pycache__/test_all.cpython-311-pytest-8.2.0.pyc
calibr8/__pycache__/utils.cpython-311.pyc
calibr8/contrib/__init__.py
calibr8/contrib/noise.py
calibr8/contrib/normal.py
calibr8/contrib/studentt.py
calibr8/contrib/__pycache__/__init__.cpython-311.pyc
calibr8/contrib/__pycache__/noise.cpython-311.pyc
calibr8/contrib/__pycache__/normal.cpython-311.pyc
calibr8/contrib/__pycache__/studentt.cpython-311.pyc
calibr8-7.1.2.dist-info/LICENSE
calibr8-7.1.2.dist-info/METADATA
calibr8-7.1.2.dist-info/WHEEL
calibr8-7.1.2.dist-info/top_level.txt
calibr8-7.1.2.dist-info/RECORD
