Metadata-Version: 2.1
Name: calibr8
Version: 7.1.2
Summary: Toolbox for non-linear calibration modeling.
Home-page: https://github.com/JuBiotech/calibr8
Author: Laura Marie Helleckes, Michael Osthege
Author-email: l.helleckes@fz-juelich.de, m.osthege@fz-juelich.de
License: GNU Affero General Public License v3
Classifier: Programming Language :: Python
Classifier: Operating System :: OS Independent
Classifier: Programming Language :: Python :: 3.7
Classifier: Programming Language :: Python :: 3.8
Classifier: Programming Language :: Python :: 3.9
Classifier: License :: OSI Approved :: GNU Affero General Public License v3
Classifier: Intended Audience :: Science/Research
Classifier: Topic :: Scientific/Engineering
Classifier: Topic :: Scientific/Engineering :: Mathematics
Requires-Python: >=3.6
License-File: LICENSE
Requires-Dist: matplotlib
Requires-Dist: numpy
Requires-Dist: scipy >1.6.0
Requires-Dist: typing-extensions
